scsampler/__init__.py
scsampler/main.py
scsampler/uclab.py
scsampler-1.0.2.dist-info/LICENCE
scsampler-1.0.2.dist-info/METADATA
scsampler-1.0.2.dist-info/WHEEL
scsampler-1.0.2.dist-info/top_level.txt
scsampler-1.0.2.dist-info/RECORD
